ejemplo1/Ej1.vhd
-- Quartus II VHDL Template
-- Signed Adder

library ieee;
use ieee.std_logic_1164.all;
use ieee.numeric_std.all;

entity Ej1 is



	port 
	(
		W	: out std_logic;
		A    : in std_logic;
		B 	: in std_logic
		
	);

end entity;

architecture rtl of Ej1 is
begin

W <= A and B;


end rtl;

ejemplo1/tb_Ej1.vhd
library ieee;
use ieee.std_logic_1164.all;


entity tb_Ej1 is
end tb_Ej1;

architecture a of tb_Ej1 is

component Ej1 is	  -- declaro componente de paridades.vhdl
	port
	(
	
		W	: out std_logic;
		A    : in std_logic;
		B 	: in std_logic
		
	);
end component;
signal In1, In2 : std_logic;
signal salida : std_logic;
begin

	uut: Ej1  port map (salida,In1, In2); -- instancio paridades
	Process 
	begin
		In1 <= '0'; wait for 10 ns;
		In2 <= '0'; wait for 10 ns;
		In1 <= '1'; wait for 10 ns;
		In2 <= '1'; wait for 10 ns;
		

		
	End process;	
end a;

ejemplo1/ejemplo1.vcd
$date
  Sat Mar 30 23:46:19 2024
$end
$version
  GHDL v0
$end
$timescale
  1 fs
$end
$scope module standard $end
$upscope $end
$scope module std_logic_1164 $end
$upscope $end
$scope module numeric_std $end
$upscope $end
$scope module tb_ej1 $end
$var reg 1 ! in1 $end
$var reg 1 " in2 $end
$var reg 1 # salida $end
$scope module uut $end
$var reg 1 $ w $end
$var reg 1 % a $end
$var reg 1 & b $end
$upscope $end
$upscope $end
$enddefinitions $end
#0
0!
U"
0#
0$
0%
U&
#10000000
0"
0&
#20000000
1!
1%
#30000000
1"
1#
1$
1&
#40000000
0!
0#
0$
0%
#50000000
0"
0&
#60000000
1!
1%
#70000000
1"
1#
1$
1&
#80000000
0!
0#
0$
0%
#90000000
0"
0&
#100000000
1!
1%
#110000000
1"
1#
1$
1&
#120000000
0!
0#
0$
0%
#130000000
0"
0&
#140000000
1!
1%
#150000000
1"
1#
1$
1&
#160000000
0!
0#
0$
0%
#170000000
0"
0&
#180000000
1!
1%
#190000000
1"
1#
1$
1&
#200000000
0!
0#
0$
0%
#210000000
0"
0&
#220000000
1!
1%
#230000000
1"
1#
1$
1&
#240000000
0!
0#
0$
0%
#250000000
0"
0&
#260000000
1!
1%
#270000000
1"
1#
1$
1&
#280000000
0!
0#
0$
0%
#290000000
0"
0&
#300000000
1!
1%
#310000000
1"
1#
1$
1&
#320000000
0!
0#
0$
0%
#330000000
0"
0&
#340000000
1!
1%
#350000000
1"
1#
1$
1&
#360000000
0!
0#
0$
0%
#370000000
0"
0&
#380000000
1!
1%
#390000000
1"
1#
1$
1&
#400000000
0!
0#
0$
0%
#410000000
0"
0&
#420000000
1!
1%
#430000000
1"
1#
1$
1&
#440000000
0!
0#
0$
0%
#450000000
0"
0&
#460000000
1!
1%
#470000000
1"
1#
1$
1&
#480000000
0!
0#
0$
0%
#490000000
0"
0&
#500000000
1!
1%
#510000000
1"
1#
1$
1&
#520000000
0!
0#
0$
0%
#530000000
0"
0&
#540000000
1!
1%
#550000000
1"
1#
1$
1&
#560000000
0!
0#
0$
0%
#570000000
0"
0&
#580000000
1!
1%
#590000000
1"
1#
1$
1&
#600000000
0!
0#
0$
0%
#610000000
0"
0&
#620000000
1!
1%
#630000000
1"
1#
1$
1&
#640000000
0!
0#
0$
0%
#650000000
0"
0&
#660000000
1!
1%
#670000000
1"
1#
1$
1&
#680000000
0!
0#
0$
0%
#690000000
0"
0&
#700000000
1!
1%
#710000000
1"
1#
1$
1&
#720000000
0!
0#
0$
0%
#730000000
0"
0&
#740000000
1!
1%
#750000000
1"
1#
1$
1&
#760000000
0!
0#
0$
0%
#770000000
0"
0&
#780000000
1!
1%
#790000000
1"
1#
1$
1&
#800000000
0!
0#
0$
0%
#810000000
0"
0&
#820000000
1!
1%
#830000000
1"
1#
1$
1&
#840000000
0!
0#
0$
0%
#850000000
0"
0&
#860000000
1!
1%
#870000000
1"
1#
1$
1&
#880000000
0!
0#
0$
0%
#890000000
0"
0&
#900000000
1!
1%
#910000000
1"
1#
1$
1&
#920000000
0!
0#
0$
0%
#930000000
0"
0&
#940000000
1!
1%
#950000000
1"
1#
1$
1&
#960000000
0!
0#
0$
0%
#970000000
0"
0&
#980000000
1!
1%
#990000000
1"
1#
1$
1&
#1000000000
0!
0#
0$
0%
